cubeparser_mcp/__init__.py
cubeparser_mcp/auth.py
cubeparser_mcp/client.py
cubeparser_mcp/server.py
cubeparser_mcp-0.1.1.dist-info/METADATA
cubeparser_mcp-0.1.1.dist-info/WHEEL
cubeparser_mcp-0.1.1.dist-info/entry_points.txt
cubeparser_mcp-0.1.1.dist-info/RECORD
