Metadata-Version: 2.4
Name: cubeparser-mcp
Version: 0.1.1
Summary: MCP Server for CubeParser document extraction API
Project-URL: Homepage, https://github.com/your-org/cubeparser-mcp
Project-URL: Repository, https://github.com/your-org/cubeparser-mcp
Project-URL: Issues, https://github.com/your-org/cubeparser-mcp/issues
Author-email: CubeParser MCP <support@example.com>
License: MIT
Keywords: api,cubeparser,document-extraction,mcp
Classifier: Development Status :: 4 - Beta
Classifier: Intended Audience :: Developers
Classifier: License :: OSI Approved :: MIT License
Classifier: Programming Language :: Python :: 3
Classifier: Programming Language :: Python :: 3.10
Classifier: Programming Language :: Python :: 3.11
Classifier: Programming Language :: Python :: 3.12
Requires-Python: >=3.10
Requires-Dist: fastmcp>=0.2.0
Requires-Dist: httpx>=0.25.0
Requires-Dist: pydantic>=2.0.0
Requires-Dist: python-dotenv>=1.0.0
